{"20508720": {"follow_request_sent": false, "has_extended_profile": false, "profile_use_background_image": true, "default_profile_image": false, "id": 20508720, "profile_background_image_url_https": "https://abs.twimg.com/images/themes/theme1/bg.png", "verified": true, "profile_text_color": "333333", "profile_image_url_https": "https://pbs.twimg.com/profile_images/77712921/greg_spic_normal.jpg", "profile_sidebar_fill_color": "DDEEF6", "entities": {"url": {"urls": [{"url": "https://t.co/Bx7pTZ6DYZ", "indices": [0, 23], "expanded_url": "https://www.washingtonpost.com/blogs/plum-line/", "display_url": "washingtonpost.com/blogs/plum-lin…"}]}, "description": {"urls": []}}, "followers_count": 86921, "profile_sidebar_border_color": "C0DEED", "id_str": "20508720", "profile_background_color": "C0DEED", "listed_count": 3692, "status": {"contributors": null, "truncated": false, "text": "@kombiz thanks man", "is_quote_status": false, "in_reply_to_status_id": 710947782253797376, "id": 710960221582139392, "favorite_count": 1, "source": "<a href=\"https://about.twitter.com/products/tweetdeck\" rel=\"nofollow\">TweetDeck</a>", "retweeted": false, "coordinates": null, "entities": {"symbols": [], "user_mentions": [{"id": 7040852, "indices": [0, 7], "id_str": "7040852", "screen_name": "kombiz", "name": "Kombiz Lavasany"}], "hashtags": [], "urls": []}, "in_reply_to_screen_name": "kombiz", "id_str": "710960221582139392", "retweet_count": 0, "in_reply_to_user_id": 7040852, "favorited": false, "geo": null, "in_reply_to_user_id_str": "7040852", "lang": "en", "created_at": "Fri Mar 18 22:45:00 +0000 2016", "in_reply_to_status_id_str": "710947782253797376", "place": null}, "is_translation_enabled": false, "utc_offset": -18000, "statuses_count": 92689, "description": "A blog about politics, politics, and politics", "friends_count": 3208, "location": "", "profile_link_color": "0084B4", "profile_image_url": "http://pbs.twimg.com/profile_images/77712921/greg_spic_normal.jpg", "following": false, "geo_enabled": true, "profile_background_image_url": "http://abs.twimg.com/images/themes/theme1/bg.png", "screen_name": "ThePlumLineGS", "lang": "en", "profile_background_tile": false, "favourites_count": 940, "name": "Greg Sargent", "notifications": false, "url": "https://t.co/Bx7pTZ6DYZ", "created_at": "Tue Feb 10 12:04:17 +0000 2009", "contributors_enabled": false, "time_zone": "Central Time (US & Canada)", "protected": false, "default_profile": true, "is_translator": false}}