{"23827692": {"follow_request_sent": false, "has_extended_profile": false, "profile_use_background_image": false, "default_profile_image": false, "id": 23827692, "profile_background_image_url_https": "https://pbs.twimg.com/profile_background_images/699850318/13ead3470e83459526f740acbfb3e13a.jpeg", "verified": true, "profile_text_color": "333333", "profile_image_url_https": "https://pbs.twimg.com/profile_images/686403214523150336/y9c8xqfi_normal.jpg", "profile_sidebar_fill_color": "B0AFAD", "entities": {"url": {"urls": [{"url": "https://t.co/v5Y7yfL9SX", "indices": [0, 23], "expanded_url": "http://cc.com", "display_url": "cc.com"}]}, "description": {"urls": []}}, "followers_count": 1390442, "profile_sidebar_border_color": "FFFFFF", "id_str": "23827692", "profile_background_color": "EDF0F5", "listed_count": 6279, "status": {"contributors": null, "truncated": false, "text": "Who needs plates? https://t.co/EyUNj5S9Bl", "is_quote_status": false, "in_reply_to_status_id": null, "id": 710979098219302914, "favorite_count": 56, "source": "<a href=\"http://www.sprinklr.com\" rel=\"nofollow\">Sprinklr</a>", "retweeted": false, "coordinates": null, "entities": {"symbols": [], "user_mentions": [], "hashtags": [], "urls": [], "media": [{"expanded_url": "http://twitter.com/ComedyCentral/status/710979098219302914/photo/1", "display_url": "pic.twitter.com/EyUNj5S9Bl", "url": "https://t.co/EyUNj5S9Bl", "media_url_https": "https://pbs.twimg.com/media/Cd3nuQNXEAATnlP.jpg", "id_str": "710979098005409792", "sizes": {"large": {"h": 576, "resize": "fit", "w": 1024}, "small": {"h": 191, "resize": "fit", "w": 340}, "medium": {"h": 338, "resize": "fit", "w": 600}, "thumb": {"h": 150, "resize": "crop", "w": 150}}, "indices": [18, 41], "type": "photo", "id": 710979098005409792, "media_url": "http://pbs.twimg.com/media/Cd3nuQNXEAATnlP.jpg"}]}, "in_reply_to_screen_name": null, "id_str": "710979098219302914", "retweet_count": 17, "in_reply_to_user_id": null, "favorited": false, "geo": null, "in_reply_to_user_id_str": null, "possibly_sensitive": false, "lang": "en", "created_at": "Sat Mar 19 00:00:01 +0000 2016", "in_reply_to_status_id_str": null, "place": null, "extended_entities": {"media": [{"expanded_url": "http://twitter.com/ComedyCentral/status/710979098219302914/photo/1", "display_url": "pic.twitter.com/EyUNj5S9Bl", "url": "https://t.co/EyUNj5S9Bl", "media_url_https": "https://pbs.twimg.com/media/Cd3nuQNXEAATnlP.jpg", "id_str": "710979098005409792", "sizes": {"large": {"h": 576, "resize": "fit", "w": 1024}, "small": {"h": 191, "resize": "fit", "w": 340}, "medium": {"h": 338, "resize": "fit", "w": 600}, "thumb": {"h": 150, "resize": "crop", "w": 150}}, "indices": [18, 41], "type": "photo", "id": 710979098005409792, "media_url": "http://pbs.twimg.com/media/Cd3nuQNXEAATnlP.jpg"}]}}, "is_translation_enabled": false, "utc_offset": -14400, "statuses_count": 71885, "description": "Finally, comedy on Twitter.", "friends_count": 10391, "location": "", "profile_link_color": "2155A8", "profile_image_url": "http://pbs.twimg.com/profile_images/686403214523150336/y9c8xqfi_normal.jpg", "following": false, "geo_enabled": false, "profile_banner_url": "https://pbs.twimg.com/profile_banners/23827692/1457652645", "profile_background_image_url": "http://pbs.twimg.com/profile_background_images/699850318/13ead3470e83459526f740acbfb3e13a.jpeg", "screen_name": "ComedyCentral", "lang": "en", "profile_background_tile": true, "favourites_count": 40580, "name": "Comedy Central", "notifications": false, "url": "https://t.co/v5Y7yfL9SX", "created_at": "Wed Mar 11 20:52:09 +0000 2009", "contributors_enabled": false, "time_zone": "Eastern Time (US & Canada)", "protected": false, "default_profile": false, "is_translator": false}}