{"58404120": {"follow_request_sent": false, "has_extended_profile": false, "profile_use_background_image": false, "default_profile_image": false, "id": 58404120, "profile_background_image_url_https": "https://pbs.twimg.com/profile_background_images/219276419/-257_2.jpg", "verified": false, "profile_text_color": "333333", "profile_image_url_https": "https://pbs.twimg.com/profile_images/670708272844943360/MX6qlIPL_normal.jpg", "profile_sidebar_fill_color": "DDEEF6", "entities": {"url": {"urls": [{"url": "https://t.co/nblNZaOOWr", "indices": [0, 23], "expanded_url": "http://tresbach.com", "display_url": "tresbach.com"}]}, "description": {"urls": []}}, "followers_count": 517, "profile_sidebar_border_color": "C0DEED", "id_str": "58404120", "profile_background_color": "C0DEED", "listed_count": 10, "status": {"contributors": null, "truncated": false, "text": "RT @_CarlosLz: Os senhores gostariam de experimentar essa nova fragrância da jequiti? https://t.co/lEeCt2ogp4", "is_quote_status": false, "in_reply_to_status_id": null, "id": 710955618010587137, "favorite_count": 0, "source": "<a href=\"http://twitter.com\" rel=\"nofollow\">Twitter Web Client</a>", "retweeted": false, "coordinates": null, "entities": {"symbols": [], "user_mentions": [{"id": 49078827, "indices": [3, 13], "id_str": "49078827", "screen_name": "_CarlosLz", "name": "House of Carlos"}], "hashtags": [], "urls": [], "media": [{"source_user_id": 49078827, "source_status_id_str": "710955028035596289", "expanded_url": "http://twitter.com/_CarlosLz/status/710955028035596289/photo/1", "display_url": "pic.twitter.com/lEeCt2ogp4", "url": "https://t.co/lEeCt2ogp4", "media_url_https": "https://pbs.twimg.com/media/Cd3R0yXW4AES_2R.jpg", "source_user_id_str": "49078827", "source_status_id": 710955028035596289, "id_str": "710955020997550081", "sizes": {"small": {"h": 227, "resize": "fit", "w": 340}, "large": {"h": 683, "resize": "fit", "w": 1024}, "medium": {"h": 400, "resize": "fit", "w": 600}, "thumb": {"h": 150, "resize": "crop", "w": 150}}, "indices": [86, 109], "type": "photo", "id": 710955020997550081, "media_url": "http://pbs.twimg.com/media/Cd3R0yXW4AES_2R.jpg"}]}, "in_reply_to_screen_name": null, "id_str": "710955618010587137", "retweet_count": 89, "in_reply_to_user_id": null, "favorited": false, "retweeted_status": {"contributors": null, "truncated": false, "text": "Os senhores gostariam de experimentar essa nova fragrância da jequiti? https://t.co/lEeCt2ogp4", "is_quote_status": false, "in_reply_to_status_id": null, "id": 710955028035596289, "favorite_count": 59, "source": "<a href=\"http://twitter.com/download/iphone\" rel=\"nofollow\">Twitter for iPhone</a>", "retweeted": false, "coordinates": null, "entities": {"symbols": [], "user_mentions": [], "hashtags": [], "urls": [], "media": [{"expanded_url": "http://twitter.com/_CarlosLz/status/710955028035596289/photo/1", "display_url": "pic.twitter.com/lEeCt2ogp4", "url": "https://t.co/lEeCt2ogp4", "media_url_https": "https://pbs.twimg.com/media/Cd3R0yXW4AES_2R.jpg", "id_str": "710955020997550081", "sizes": {"small": {"h": 227, "resize": "fit", "w": 340}, "large": {"h": 683, "resize": "fit", "w": 1024}, "medium": {"h": 400, "resize": "fit", "w": 600}, "thumb": {"h": 150, "resize": "crop", "w": 150}}, "indices": [71, 94], "type": "photo", "id": 710955020997550081, "media_url": "http://pbs.twimg.com/media/Cd3R0yXW4AES_2R.jpg"}]}, "in_reply_to_screen_name": null, "id_str": "710955028035596289", "retweet_count": 89, "in_reply_to_user_id": null, "favorited": false, "geo": null, "in_reply_to_user_id_str": null, "possibly_sensitive": false, "lang": "pt", "created_at": "Fri Mar 18 22:24:22 +0000 2016", "in_reply_to_status_id_str": null, "place": null, "extended_entities": {"media": [{"expanded_url": "http://twitter.com/_CarlosLz/status/710955028035596289/photo/1", "display_url": "pic.twitter.com/lEeCt2ogp4", "url": "https://t.co/lEeCt2ogp4", "media_url_https": "https://pbs.twimg.com/media/Cd3R0yXW4AES_2R.jpg", "id_str": "710955020997550081", "sizes": {"small": {"h": 227, "resize": "fit", "w": 340}, "large": {"h": 683, "resize": "fit", "w": 1024}, "medium": {"h": 400, "resize": "fit", "w": 600}, "thumb": {"h": 150, "resize": "crop", "w": 150}}, "indices": [71, 94], "type": "photo", "id": 710955020997550081, "media_url": "http://pbs.twimg.com/media/Cd3R0yXW4AES_2R.jpg"}]}}, "geo": null, "in_reply_to_user_id_str": null, "possibly_sensitive": false, "lang": "pt", "created_at": "Fri Mar 18 22:26:42 +0000 2016", "in_reply_to_status_id_str": null, "place": null, "extended_entities": {"media": [{"source_user_id": 49078827, "source_status_id_str": "710955028035596289", "expanded_url": "http://twitter.com/_CarlosLz/status/710955028035596289/photo/1", "display_url": "pic.twitter.com/lEeCt2ogp4", "url": "https://t.co/lEeCt2ogp4", "media_url_https": "https://pbs.twimg.com/media/Cd3R0yXW4AES_2R.jpg", "source_user_id_str": "49078827", "source_status_id": 710955028035596289, "id_str": "710955020997550081", "sizes": {"small": {"h": 227, "resize": "fit", "w": 340}, "large": {"h": 683, "resize": "fit", "w": 1024}, "medium": {"h": 400, "resize": "fit", "w": 600}, "thumb": {"h": 150, "resize": "crop", "w": 150}}, "indices": [86, 109], "type": "photo", "id": 710955020997550081, "media_url": "http://pbs.twimg.com/media/Cd3R0yXW4AES_2R.jpg"}]}}, "is_translation_enabled": false, "utc_offset": -18000, "statuses_count": 1892, "description": "At the intersection of languages and mundos. Basic in training. Currently @elasticaoficial | Ed: @MedillSchool, @NorthwesternU, @FGV, @UWCCostaRica", "friends_count": 2198, "location": "São Paulo", "profile_link_color": "0084B4", "profile_image_url": "http://pbs.twimg.com/profile_images/670708272844943360/MX6qlIPL_normal.jpg", "following": false, "geo_enabled": true, "profile_banner_url": "https://pbs.twimg.com/profile_banners/58404120/1381714061", "profile_background_image_url": "http://pbs.twimg.com/profile_background_images/219276419/-257_2.jpg", "screen_name": "fabianohtl", "lang": "en", "profile_background_tile": false, "favourites_count": 504, "name": "Fabiano Tresbach", "notifications": false, "url": "https://t.co/nblNZaOOWr", "created_at": "Mon Jul 20 05:57:48 +0000 2009", "contributors_enabled": false, "time_zone": "Central Time (US & Canada)", "protected": false, "default_profile": false, "is_translator": false}}